photoprysm/__init__.py
photoprysm/__main__.py
photoprysm/core.py
photoprysm/api/__init__.py
photoprysm/api/albums.py
photoprysm/api/photos.py
photoprysm/models/__init__.py
photoprysm/models/albums.py
photoprysm/models/base.py
photoprysm/models/links.py
photoprysm/models/photos.py
photoprysm-0.0.3.dist-info/AUTHORS.rst
photoprysm-0.0.3.dist-info/LICENSE
photoprysm-0.0.3.dist-info/METADATA
photoprysm-0.0.3.dist-info/WHEEL
photoprysm-0.0.3.dist-info/top_level.txt
photoprysm-0.0.3.dist-info/RECORD
