Metadata-Version: 2.2
Name: photoprysm
Version: 0.0.3
Summary: A Python client for interacting the the Photoprism REST API.
Author-email: Rice Rodriguez <victoriarice@protonmail.com>
Maintainer-email: Rice Rodriguez <victoriarice@protonmail.com>
License: GNU General Public License v3
Project-URL: bugs, https://github.com/ricerodriguez/photoprysm/issues
Project-URL: changelog, https://github.com/ricerodriguez/photoprysm/blob/master/changelog.md
Project-URL: homepage, https://github.com/ricerodriguez/photoprysm
License-File: LICENSE
License-File: AUTHORS.rst
Requires-Dist: requests>=2.32.3
Provides-Extra: dev
Requires-Dist: pytest; extra == "dev"
Requires-Dist: responses; extra == "dev"
Provides-Extra: doc
Requires-Dist: sphinx; extra == "doc"
Requires-Dist: sphinx_autodoc_typehints; extra == "doc"
